dynamical_networks/__init__.py
dynamical_networks/analysis/__init__.py
dynamical_networks/analysis/evolutionary_homology.py
dynamical_networks/analysis/statistics.py
dynamical_networks/simulate/MS_network.py
dynamical_networks/simulate/PG_network.py
dynamical_networks/simulate/__init__.py
dynamical_networks/simulate/lorenz_network.py
dynamical_networks/simulate/vicsek_network.py
dynamical_networks/test/__init__.py
dynamical_networks/test/test_MS_network.py
dynamical_networks/test/test_evolutionary_homology.py
dynamical_networks/test/test_statistics.py
dynamical_networks-0.1.4.dist-info/LICENSE
dynamical_networks-0.1.4.dist-info/METADATA
dynamical_networks-0.1.4.dist-info/WHEEL
dynamical_networks-0.1.4.dist-info/top_level.txt
dynamical_networks-0.1.4.dist-info/RECORD
