Metadata-Version: 2.1
Name: dynamical-networks
Version: 0.1.4
Summary: A package for dynamical networks simulations and analysis.
Home-page: https://github.com/myersau3/Dynamical_Networks
Author: Audun Myers
Author-email: myersau3@msu.edu
License: UNKNOWN
Platform: UNKNOWN
Classifier: Programming Language :: Python :: 3
Classifier: License :: OSI Approved :: MIT License
Classifier: Operating System :: OS Independent
Requires-Python: >=3.6
